huscy/project_documents/__init__.py
huscy/project_documents/admin.py
huscy/project_documents/apps.py
huscy/project_documents/models.py
huscy/project_documents/permissions.py
huscy/project_documents/serializer.py
huscy/project_documents/services.py
huscy/project_documents/urls.py
huscy/project_documents/views.py
huscy/project_documents/migrations/0001_initial.py
huscy/project_documents/migrations/0002_auto_20211028_0738.py
huscy/project_documents/migrations/__init__.py
huscy.project_documents-1.4.2.dist-info/LICENSE
huscy.project_documents-1.4.2.dist-info/METADATA
huscy.project_documents-1.4.2.dist-info/WHEEL
huscy.project_documents-1.4.2.dist-info/top_level.txt
huscy.project_documents-1.4.2.dist-info/RECORD
